outlook_msg/__init__.py
outlook_msg/attachment.py
outlook_msg/constants.py
outlook_msg/message.py
outlook_msg/message_file_storage.py
outlook_msg/property.py
outlook_msg/property_tag.py
outlook_msg-1.0.0.dist-info/LICENSE
outlook_msg-1.0.0.dist-info/METADATA
outlook_msg-1.0.0.dist-info/WHEEL
outlook_msg-1.0.0.dist-info/top_level.txt
outlook_msg-1.0.0.dist-info/RECORD
