Metadata-Version: 2.1
Name: outlook-msg
Version: 1.0.0
Summary: Read contents, metadata and attachments from Outlook Message files
Home-page: https://github.com/HamiltonInsurance/outlook_msg
Author: Hamilton Insurance Group
Author-email: opensource@hamiltoninsurancegroup.com
License: UNKNOWN
Platform: UNKNOWN
Classifier: Programming Language :: Python :: 3
Classifier: License :: OSI Approved :: Apache Software License
Classifier: Operating System :: OS Independent
Classifier: Programming Language :: Python :: 3.6
Classifier: Programming Language :: Python :: 3.7
Classifier: Development Status :: 5 - Production/Stable
Classifier: Intended Audience :: Developers
Classifier: Intended Audience :: Financial and Insurance Industry
Classifier: Topic :: Communications :: Email
Classifier: Topic :: Office/Business
Classifier: Topic :: Software Development :: Libraries :: Python Modules
Requires-Python: >=3.6, <4
Requires-Dist: compoundfiles (~=0.3)
